odoo/addons/l10n_th_sequence_qoy/README.rst
odoo/addons/l10n_th_sequence_qoy/__init__.py
odoo/addons/l10n_th_sequence_qoy/__manifest__.py
odoo/addons/l10n_th_sequence_qoy/i18n/l10n_th_sequence_qoy.pot
odoo/addons/l10n_th_sequence_qoy/models/__init__.py
odoo/addons/l10n_th_sequence_qoy/models/ir_sequence.py
odoo/addons/l10n_th_sequence_qoy/readme/CONTRIBUTORS.rst
odoo/addons/l10n_th_sequence_qoy/readme/DESCRIPTION.rst
odoo/addons/l10n_th_sequence_qoy/readme/HISTORY.rst
odoo/addons/l10n_th_sequence_qoy/static/description/icon.png
odoo/addons/l10n_th_sequence_qoy/static/description/index.html
odoo/addons/l10n_th_sequence_qoy/tests/__init__.py
odoo/addons/l10n_th_sequence_qoy/tests/test_ir_sequence.py
odoo/addons/l10n_th_sequence_qoy/views/ir_sequence_view.xml
odoo14_addon_l10n_th_sequence_qoy-14.0.1.0.1.dist-info/METADATA
odoo14_addon_l10n_th_sequence_qoy-14.0.1.0.1.dist-info/WHEEL
odoo14_addon_l10n_th_sequence_qoy-14.0.1.0.1.dist-info/top_level.txt
odoo14_addon_l10n_th_sequence_qoy-14.0.1.0.1.dist-info/RECORD
